cyslf/.DS_Store
cyslf/__init__.py
cyslf/constraints.py
cyslf/convert_addresses.py
cyslf/cyslf.py
cyslf/make_teams.py
cyslf/models.py
cyslf/optimize.py
cyslf/prepare_player_data.py
cyslf/scorers/__init__.py
cyslf/scorers/base.py
cyslf/scorers/core.py
cyslf/utils.py
cyslf/validation.py
cyslf-0.2.13.dist-info/METADATA
cyslf-0.2.13.dist-info/WHEEL
cyslf-0.2.13.dist-info/entry_points.txt
cyslf-0.2.13.dist-info/RECORD
