Metadata-Version: 2.1
Name: cyslf
Version: 0.2.13
Summary: CYS League Formation
License: MIT
Author: Evan Tey
Author-email: evantey14@gmail.com
Requires-Python: >=3.8,<4.0
Classifier: License :: OSI Approved :: MIT License
Classifier: Programming Language :: Python :: 3
Classifier: Programming Language :: Python :: 3.8
Classifier: Programming Language :: Python :: 3.9
Classifier: Programming Language :: Python :: 3.10
Classifier: Programming Language :: Python :: 3.11
Requires-Dist: geopy (>=2.2.0,<3.0.0)
Requires-Dist: numpy (>=1.21.3,<2.0.0)
Requires-Dist: pandas (>=1.4.3,<2.0.0)
Requires-Dist: thefuzz (>=0.19.0,<0.20.0)
Requires-Dist: tqdm (>=4.64.0,<5.0.0)
